LICENSE
MANIFEST.in
README.md
setup.py
../LICENSE
../README.md
hsmlfix/__init__.py
hsmlfix/connection.py
hsmlfix/constants.py
hsmlfix/decorators.py
hsmlfix/model.py
hsmlfix/model_registry.py
hsmlfix/tag.py
hsmlfix/util.py
hsmlfix/version.py
hsmlfix.egg-info/PKG-INFO
hsmlfix.egg-info/SOURCES.txt
hsmlfix.egg-info/dependency_links.txt
hsmlfix.egg-info/requires.txt
hsmlfix.egg-info/top_level.txt
hsmlfix/client/__init__.py
hsmlfix/client/auth.py
hsmlfix/client/base.py
hsmlfix/client/exceptions.py
hsmlfix/client/external.py
hsmlfix/client/hopsworks.py
hsmlfix/core/__init__.py
hsmlfix/core/dataset_api.py
hsmlfix/core/model_api.py
hsmlfix/core/model_registry_api.py
hsmlfix/core/native_hdfs_api.py
hsmlfix/engine/__init__.py
hsmlfix/engine/hopsworks_engine.py
hsmlfix/engine/local_engine.py
hsmlfix/engine/model_engine.py
hsmlfix/python/__init__.py
hsmlfix/python/model.py
hsmlfix/python/signature.py
hsmlfix/sklearn/__init__.py
hsmlfix/sklearn/model.py
hsmlfix/sklearn/signature.py
hsmlfix/tensorflow/__init__.py
hsmlfix/tensorflow/model.py
hsmlfix/tensorflow/signature.py
hsmlfix/torch/__init__.py
hsmlfix/torch/model.py
hsmlfix/torch/signature.py
hsmlfix/utils/__init__.py
hsmlfix/utils/column.py
hsmlfix/utils/columnar_schema.py
hsmlfix/utils/model_schema.py
hsmlfix/utils/schema.py
hsmlfix/utils/tensor.py
hsmlfix/utils/tensor_schema.py
tests/__init__.py
tests/hsml/__init__.py
tests/hsml/core/__init__.py